CHANGELOG.md
LICENSE
MANIFEST.in
README.md
setup.py
Rambo_vagrant.egg-info/PKG-INFO
Rambo_vagrant.egg-info/SOURCES.txt
Rambo_vagrant.egg-info/dependency_links.txt
Rambo_vagrant.egg-info/entry_points.txt
Rambo_vagrant.egg-info/not-zip-safe
Rambo_vagrant.egg-info/requires.txt
Rambo_vagrant.egg-info/top_level.txt
docs/CHANGELOG.md
docs/Makefile
docs/conf.py
docs/index.rst
docs/_static/custom.css
docs/_templates/layout.html
docs/core/api.md
docs/core/cli.md
docs/core/conf.md
docs/core/customizing.md
docs/core/env_vars.md
docs/core/quickstart.md
docs/providers/aws-ec2.md
docs/providers/digitalocean.md
docs/providers/docker.md
docs/providers/lxc.md
rambo/Vagrantfile
rambo/__init__.py
rambo/app.py
rambo/cli.py
rambo/click_configfile.py
rambo/providers.py
rambo/scripts.py
rambo/settings.json
rambo/settings.py
rambo/utils.py
rambo/auth/env_scripts/aws.env.sh.dist
rambo/auth/env_scripts/digitalocean.env.sh.dist
rambo/click-configfile/.bumpversion.cfg
rambo/click-configfile/.coveragerc
rambo/click-configfile/.git
rambo/click-configfile/.gitignore
rambo/click-configfile/.pylintrc
rambo/click-configfile/.travis.yml
rambo/click-configfile/LICENSE
rambo/click-configfile/MANIFEST.in
rambo/click-configfile/PROJECT_INFO.rst
rambo/click-configfile/README.rst
rambo/click-configfile/click_configfile.py
rambo/click-configfile/invoke.yaml
rambo/click-configfile/pytest.ini
rambo/click-configfile/setup.cfg
rambo/click-configfile/setup.py
rambo/click-configfile/tox.ini
rambo/click-configfile/.ci/appveyor.yml
rambo/click-configfile/py.requirements/all.txt
rambo/click-configfile/py.requirements/basic.txt
rambo/click-configfile/py.requirements/develop.txt
rambo/click-configfile/py.requirements/testing.txt
rambo/click-configfile/tasks/__init__.py
rambo/click-configfile/tasks/__main__.py
rambo/click-configfile/tasks/_setup.py
rambo/click-configfile/tasks/clean.py
rambo/click-configfile/tasks/docs.py
rambo/click-configfile/tasks/requirements.txt
rambo/click-configfile/tasks/test.py
rambo/click-configfile/tasks/_vendor/README.rst
rambo/click-configfile/tasks/_vendor/invoke.zip
rambo/click-configfile/tasks/_vendor/path.py
rambo/click-configfile/tasks/_vendor/pathlib.py
rambo/click-configfile/tasks/_vendor/six.py
rambo/click-configfile/tests/__init__.py
