Metadata-Version: 1.1
Name: Rambo-vagrant
Version: 0.4.4
Summary: A Provider Agnostic Provioning Framework
Home-page: https://github.com/terminal-labs/rambo
Author: Terminal Labs
Author-email: solutions@terminallabs.com
License: Type license() to see the full license text
Platform: UNKNOWN
Classifier: Programming Language :: Python :: 3.2
Classifier: Programming Language :: Python :: 3.3
Classifier: Programming Language :: Python :: 3.4
Classifier: Programming Language :: Python :: 3.5
Classifier: Programming Language :: Python :: 3.6
